tusky.py
tusky-0.0.0.dist-info/WHEEL
tusky-0.0.0.dist-info/METADATA
tusky-0.0.0.dist-info/RECORD
